parallaxapis_sdk_py/__init__.py
parallaxapis_sdk_py/constants.py
parallaxapis_sdk_py/datadome.py
parallaxapis_sdk_py/exceptions.py
parallaxapis_sdk_py/perimeterx.py
parallaxapis_sdk_py/sdk.py
parallaxapis_sdk_py/solutions.py
parallaxapis_sdk_py/tasks.py
parallaxapis_sdk_py-1.2.4.dist-info/licenses/LICENSE
parallaxapis_sdk_py-1.2.4.dist-info/WHEEL
parallaxapis_sdk_py-1.2.4.dist-info/METADATA
parallaxapis_sdk_py-1.2.4.dist-info/RECORD
