Metadata-Version: 2.4
Name: parallaxapis-sdk-py
Version: 1.2.4
Summary: ParallaxAPIs SDK
Keywords: perimeterx,datadome,web scraping,bot detection,anti-bot,bypass,captcha solver,typescript,javascript,nodejs,automation,headless browser,sensor data,challenge solver,cookie generation,fingerprinting,crawlers,bot mitigation,sdk,request-based
Author: ParallaxSystems
Author-email: ParallaxSystems <info@parallaxsystems.io>
License-Expression: MIT
License-File: LICENSE
Requires-Dist: httpx[http2]>=0.28.1
Requires-Dist: pydantic>=2.12.0
Requires-Python: >=3.11
Project-URL: Homepage, https://www.parallaxsystems.io/join?s=pip
Project-URL: Repository, https://github.com/ParallaxAPIs/parallaxapis-sdk-py
